LICENSE
MANIFEST.in
README.rst
requirements.txt
setup.py
django_meetup.egg-info/PKG-INFO
django_meetup.egg-info/SOURCES.txt
django_meetup.egg-info/dependency_links.txt
django_meetup.egg-info/requires.txt
django_meetup.egg-info/top_level.txt
meetup/__init__.py
meetup/admin.py
meetup/api.py
meetup/models.py
meetup/sync.py
meetup/sync_utils.py
meetup/views.py
meetup/management/__init__.py
meetup/management/commands/__init__.py
meetup/management/commands/sync_group_events.py
meetup/tests/__init__.py
meetup/tests/test_api.py
meetup/tests/test_models_sync.py
meetup/tests/test_sync_utils.py
meetup/tests/tests.py