Metadata-Version: 1.1
Name: django-meetup
Version: 1.0.7
Summary: General purpose tool to sync a local database with Meetup.com content
Home-page: https://github.com/astrodsg/django-meetup
Author: Dylan Gregersen
Author-email: gregersen.dylan@gmail.com
License: 3-clause BSD style license
Platform: any
Classifier: Intended Audience :: Developers
Classifier: License :: OSI Approved :: BSD License
Classifier: Natural Language :: English
Classifier: Operating System :: OS Independent
Classifier: Programming Language :: Python
Classifier: Topic :: Software Development :: Libraries :: Python Modules
